3p_hrdevhelper_ida_plugin-2025.6.6.dist-info/licenses/LICENSE
hrdh/__init__.py
hrdh/config.py
hrdh/contextview.py
hrdh/graph.py
hrdh/handler.py
hrdh/hrdevhelper.py
hrdh/tools.py
3p_hrdevhelper_ida_plugin-2025.6.6.dist-info/METADATA
3p_hrdevhelper_ida_plugin-2025.6.6.dist-info/WHEEL
3p_hrdevhelper_ida_plugin-2025.6.6.dist-info/entry_points.txt
3p_hrdevhelper_ida_plugin-2025.6.6.dist-info/top_level.txt
3p_hrdevhelper_ida_plugin-2025.6.6.dist-info/RECORD
