Metadata-Version: 2.4
Name: 3p-HRDevHelper-ida-plugin
Version: 2025.6.6
Summary: A helpful tool for debugging and developing your own Hexrays plugins and scripts
Author: Dennis Elser
Maintainer-email: Willi Ballenthin <willi.ballenthin@gmail.com>
Project-URL: source, https://github.com/patois/HRDevHelper
Project-URL: repository, https://github.com/patois/HRDevHelper
Project-URL: plugin-source, https://github.com/williballenthin/idawilli/tree/master/plugins/plugin-manager/3p-plugins/
Requires-Python: >=3.9
License-File: LICENSE
Dynamic: license-file
